pyphetools/__init__.py
pyphetools/creation/__init__.py
pyphetools/creation/abstract_encoder.py
pyphetools/creation/age_column_mapper.py
pyphetools/creation/age_isoformater.py
pyphetools/creation/allelic_requirement.py
pyphetools/creation/case_template_encoder.py
pyphetools/creation/citation.py
pyphetools/creation/cohort_encoder.py
pyphetools/creation/column_mapper.py
pyphetools/creation/constant_column_mapper.py
pyphetools/creation/constants.py
pyphetools/creation/create_template.py
pyphetools/creation/discombulator.py
pyphetools/creation/disease.py
pyphetools/creation/disease_id_column_mapper.py
pyphetools/creation/hgvs_variant.py
pyphetools/creation/hp_term.py
pyphetools/creation/hpo_base_cr.py
pyphetools/creation/hpo_cr.py
pyphetools/creation/hpo_exact_cr.py
pyphetools/creation/hpo_fasthpocr_cr.py
pyphetools/creation/hpo_parser.py
pyphetools/creation/import_template.py
pyphetools/creation/individual.py
pyphetools/creation/intergenic_variant.py
pyphetools/creation/measurements.py
pyphetools/creation/metadata.py
pyphetools/creation/mode_of_inheritance.py
pyphetools/creation/ontology_terms.py
pyphetools/creation/pyphetools_age.py
pyphetools/creation/sex_column_mapper.py
pyphetools/creation/simple_column_mapper.py
pyphetools/creation/structural_variant.py
pyphetools/creation/thresholded_column_mapper.py
pyphetools/creation/thresholder.py
pyphetools/creation/variant.py
pyphetools/creation/variant_column_mapper.py
pyphetools/creation/variant_manager.py
pyphetools/creation/variant_validator.py
pyphetools/creation/data/thresholds.tsv
pyphetools/pp/__init__.py
pyphetools/pp/_api.py
pyphetools/pp/_timestamp.py
pyphetools/pp/parse/__init__.py
pyphetools/pp/parse/_io.py
pyphetools/pp/parse/_pb.py
pyphetools/pp/parse/_test_util.py
pyphetools/pp/parse/_util.py
pyphetools/pp/parse/json/__init__.py
pyphetools/pp/parse/json/_json.py
pyphetools/pp/v202/__init__.py
pyphetools/pp/v202/_base.py
pyphetools/pp/v202/_biosample.py
pyphetools/pp/v202/_disease.py
pyphetools-0.9.119.dist-info/licenses/LICENSE
pyphetools-0.9.119.dist-info/METADATA
pyphetools-0.9.119.dist-info/WHEEL
pyphetools-0.9.119.dist-info/top_level.txt
pyphetools-0.9.119.dist-info/RECORD
