Metadata-Version: 2.4
Name: pyphetools
Version: 0.9.119
Summary: Generate and work with GA4GH phenopackets
Author-email: Peter Robinson <peter.robinson@bih-charite.de>, Daniel Danis <daniel.gordon.danis@protonmail.com>
License: MIT License
Project-URL: homepage, https://github.com/monarch-initiative/pyphetools
Project-URL: repository, https://github.com/monarch-initiative/pyphetools.git
Project-URL: documentation, https://github.com/monarch-initiative/pyphetools
Project-URL: bugtracker, https://github.com/monarch-initiative/pyphetools/issues
Keywords: Global Alliance for Genomics and Health,GA4GH Phenopacket Schema,Human Phenotype Ontology,GA4GH,HPO
Classifier: Development Status :: 3 - Alpha
Classifier: License :: OSI Approved :: MIT License
Classifier: Operating System :: OS Independent
Classifier: Programming Language :: Python :: 3
Requires-Python: >=3.8
License-File: LICENSE
Requires-Dist: hpo-toolkit<0.8.0,>=0.5.0
Requires-Dist: matplotlib<4.0,>=3.2.0
Requires-Dist: pandas[excel]<3.0.0,>=2.0.0
Requires-Dist: phenopackets>=2.0.2
Requires-Dist: protobuf<4.0.0,>=3.15.0
Requires-Dist: requests<3.0,>=2.25.0
Requires-Dist: fasthpocr>=0.1.0
Provides-Extra: test
Requires-Dist: pytest<8.0.0,>=7.0.0; extra == "test"
Provides-Extra: docs
Requires-Dist: mkdocs-material[imaging]<10,>=9.5.10; extra == "docs"
Requires-Dist: mkdocs-material-extensions<2.0,>=1.3; extra == "docs"
Requires-Dist: mkdocstrings[python]<1.0,>=0.22; extra == "docs"
Requires-Dist: pillow; extra == "docs"
Requires-Dist: cairosvg; extra == "docs"
Dynamic: license-file
